{
  "sha": "6c8f531c57bab85fca175dd0c7b21363a4c8767c",
  "message": "Simplify database.py: replace migrations with direct table creation\n\n- Remove migration system (migrate_v1-v4, schema_version tracking)\n- Add create_tables() function that creates all tables directly\n- Add decks table for organizing voice personas into themed collections\n- Add voices table for individual voice personas within decks\n- Consolidate v1-v4 migrations into single clean schema",
  "author": {
    "name": "lexicalmathical",
    "email": "lexicalmathical@gmail.com",
    "date": "2025-11-13T09:37:10Z"
  },
  "committer": {
    "name": "lexicalmathical",
    "email": "lexicalmathical@gmail.com",
    "date": "2025-11-13T09:37:10Z"
  },
  "stats": {
    "total": 156,
    "additions": 55,
    "deletions": 101
  },
  "files_count": 1,
  "parents": [
    "07aaff86a658c5cf0d8ef3d24462dc03fb917c91"
  ]
}